orbit/__init__.py
orbit/callback.py
orbit/engine.py
orbit/dataset/__init__.py
orbit/dataset/cogn.py
orbit/dataset/data/cogn_en.jsonl
orbit/dataset/data/cogn_zh.jsonl
orbit/kit/__init__.py
orbit/kit/interface.py
orbit/kit/token.py
orbit/kit/wrapper.py
orbit/model/__init__.py
orbit/model/base.py
orbit/model/config.py
orbit/model/registry.py
orbit/model/block/__init__.py
orbit/model/block/attention.py
orbit/model/block/bio.py
orbit/model/block/codebook.py
orbit/model/block/conv.py
orbit/model/block/embedding.py
orbit/model/block/film.py
orbit/model/block/fusion.py
orbit/model/block/gate.py
orbit/model/block/lora.py
orbit/model/block/mlp.py
orbit/model/block/moe.py
orbit/model/block/tcn.py
orbit/model/kit/__init__.py
orbit/model/kit/discriminator.py
orbit/model/kit/losses.py
orbit/model/motif/__init__.py
orbit/model/motif/algorithm/__init__.py
orbit/model/motif/algorithm/a1.py
orbit/model/motif/vision/__init__.py
orbit/model/motif/vision/v1.py
orbit/optim/__init__.py
orbit/optim/muon.py
orbit/optim/sam.py
orbit/plugin/__init__.py
orbit/plugin/board.py
orbit/plugin/checkpoint.py
orbit/plugin/classification.py
orbit/plugin/display_model.py
orbit/plugin/early_stopping.py
orbit/plugin/ema.py
orbit/plugin/gradient_accumulation.py
orbit/plugin/lora.py
orbit/plugin/memory_estimator.py
orbit/plugin/mentor.py
orbit/plugin/overfit.py
orbit/plugin/warmup.py
orbit/plugin/data/mentor_i18n.json
orbit/utils/__init__.py
orbit/utils/cuda.py
orbit/utils/freeze.py
orbit/utils/image.py
orbit/utils/initialization.py
orbit/utils/layer_io.py
orbit/utils/lora.py
orbit/utils/mask.py
orbit/utils/moe.py
orbit/utils/seed.py
orbit/utils/sft.py
orbit_torch-0.1.0.dist-info/METADATA
orbit_torch-0.1.0.dist-info/WHEEL
orbit_torch-0.1.0.dist-info/top_level.txt
orbit_torch-0.1.0.dist-info/RECORD
