Metadata-Version: 2.4
Name: orbit-torch
Version: 0.1.0
Summary: A PyTorch training engine with plugin system and advanced model components
Home-page: https://github.com/A03HCY/Orbit
Author: Aiden Hopkins
Author-email: acdphc@qq.com
Classifier: Programming Language :: Python :: 3
Classifier: License :: OSI Approved :: MIT License
Classifier: Operating System :: OS Independent
Requires-Python: >=3.8
Requires-Dist: torch>=2.0.0
Requires-Dist: rich
Requires-Dist: tensorboard
Requires-Dist: matplotlib
Requires-Dist: seaborn
Requires-Dist: numpy
Requires-Dist: scikit-learn
Requires-Dist: einops
Requires-Dist: tokenizers
Requires-Dist: transformers
Requires-Dist: safetensors
Requires-Dist: accelerate
Requires-Dist: lpips
Dynamic: author
Dynamic: author-email
Dynamic: classifier
Dynamic: description
Dynamic: description-content-type
Dynamic: home-page
Dynamic: requires-dist
Dynamic: requires-python
Dynamic: summary
